{"type":"FeatureCollection","name":"Mountlake Terrace_station_and_jurisdiction_data","crs":{"type":"name","properties":{"name":"urn:ogc:def:crs:OGC:1.3:CRS84"}},"features":[{"type":"Feature","properties":{"JURISDICTION_ID":"G53047490","STATION_ID":"S49014145"},"geometry":{"type":"Point","coordinates":[-122.31634,47.79898]}},{"type":"Feature","properties":{"JURISDICTION_ID":"G53047490","STATION_ID":"S1679635316"},"geometry":{"type":"Point","coordinates":[-122.31486,47.78548]}}]}