{"type":"FeatureCollection","name":"Kenmore_station_and_jurisdiction_data","crs":{"type":"name","properties":{"name":"urn:ogc:def:crs:OGC:1.3:CRS84"}},"features":[{"type":"Feature","properties":{"JURISDICTION_ID":"G53035170","STATION_ID":"S1368175279"},"geometry":{"type":"Point","coordinates":[-122.26233,47.75838]}},{"type":"Feature","properties":{"JURISDICTION_ID":"G53035170","STATION_ID":"S1368175403"},"geometry":{"type":"Point","coordinates":[-122.2536,47.75868]}},{"type":"Feature","properties":{"JURISDICTION_ID":"G53035170","STATION_ID":"S384251920"},"geometry":{"type":"Point","coordinates":[-122.23696,47.75628]}}]}