{
"type": "FeatureCollection",
"name": "Edmonds_station_and_jurisdiction_data",
"crs": { "type": "name", "properties": { "name": "urn:ogc:def:crs:OGC:1.3:CRS84" } },
"features": [
{ "type": "Feature", "properties": { "GISJOIN": "G53020750", "STATEFP": 53, "PLACEFP": 20750, "PLACENS": 2410403, "GEOID": "5320750", "NAME": "236th Street", "NAMELSAD": "Edmonds city", "LSAD": 25, "CLASSFP": "C1", "PCICBSA": "N", "PCINECTA": "N", "MTFCC": "G4110", "FUNCSTAT": "A", "ALAND": 23093351, "ALAND_sq_mi": 8.916392669, "AWATER": 2823712, "INTPTLAT": 47.8136037, "INTPTLON": -122.3533299, "Shape_Leng": 38393.03819, "Shape_Area": 23229395.36, "NHPD_Units": 225, "Permits": 2315, "Pop": 42347, "Pop_density": 4749.342203, "Non_white_share": 0.251706142, "White_non_hisp": 0.748293858, "Black_non_hisp": 0.015892507, "Asian_non_Hisp": 0.092899143, "Hispanic": 0.07948615, "Workers": 21563, "Transit_to_work": 0.08407921, "Walk_to_Work": 0.02360525, "Bike_to_work": 0.007049112, "Green_commute_share": 0.114733571, "BA_plus_25_plus": 0.489292955, "Med_HH_inc": 91499, "Cost_burdened": 0.456154796, "Very_cost_burdened": 0.193906958, "Med_housing_value": 587200, "Jobs": 13769, "Job_density": 1544.234368, "Housing_units": 18847, "Housing_density": 394.1765218, "Permit_density": 259.6341464, "Permits_per_capita": 54.66739084, "Subsidized_hsg_share": 0.01193824, "existing_housing_units": 2457, "baseline_under_zoning": 20935, "plexify_reform": 23529, "multiply_reform": 28376, "legalize_reform": 22723, "middle_reform": 22930, "all_reforms": 34701, "station_link": "236th Street-Swift Blue Line-Bus Rapid Transit-existing", "existing_housing_units.1": 1200, "baseline_under_zoning.1": 8420, "plexify_reform.1": 11045, "multiply_reform.1": 13657, "legalize_reform.1": 8420, "middle_reform.1": 8817, "all_reforms.1": 16679, "grade": "at grade", "status": "existing", "year_open": 2009, "mode": "Bus Rapid Transit", "line": "Swift Blue Line" }, "geometry": { "type": "Point", "coordinates": [ -122.34221, 47.78514 ] } },
{ "type": "Feature", "properties": { "GISJOIN": "G53020750", "STATEFP": 53, "PLACEFP": 20750, "PLACENS": 2410403, "GEOID": "5320750", "NAME": "Edmonds", "NAMELSAD": "Edmonds city", "LSAD": 25, "CLASSFP": "C1", "PCICBSA": "N", "PCINECTA": "N", "MTFCC": "G4110", "FUNCSTAT": "A", "ALAND": 23093351, "ALAND_sq_mi": 8.916392669, "AWATER": 2823712, "INTPTLAT": 47.8136037, "INTPTLON": -122.3533299, "Shape_Leng": 38393.03819, "Shape_Area": 23229395.36, "NHPD_Units": 225, "Permits": 2315, "Pop": 42347, "Pop_density": 4749.342203, "Non_white_share": 0.251706142, "White_non_hisp": 0.748293858, "Black_non_hisp": 0.015892507, "Asian_non_Hisp": 0.092899143, "Hispanic": 0.07948615, "Workers": 21563, "Transit_to_work": 0.08407921, "Walk_to_Work": 0.02360525, "Bike_to_work": 0.007049112, "Green_commute_share": 0.114733571, "BA_plus_25_plus": 0.489292955, "Med_HH_inc": 91499, "Cost_burdened": 0.456154796, "Very_cost_burdened": 0.193906958, "Med_housing_value": 587200, "Jobs": 13769, "Job_density": 1544.234368, "Housing_units": 18847, "Housing_density": 394.1765218, "Permit_density": 259.6341464, "Permits_per_capita": 54.66739084, "Subsidized_hsg_share": 0.01193824, "existing_housing_units": 2457, "baseline_under_zoning": 20935, "plexify_reform": 23529, "multiply_reform": 28376, "legalize_reform": 22723, "middle_reform": 22930, "all_reforms": 34701, "station_link": "Edmonds-Sounder-Commuter Rail-existing", "existing_housing_units.1": 746, "baseline_under_zoning.1": 4547, "plexify_reform.1": 4765, "multiply_reform.1": 4992, "legalize_reform.1": 4593, "middle_reform.1": 5845, "all_reforms.1": 6502, "grade": "at grade", "status": "existing", "year_open": 1957, "mode": "Commuter Rail", "line": "Sounder" }, "geometry": { "type": "Point", "coordinates": [ -122.38502, 47.81073 ] } }
]
}
