{
"type": "FeatureCollection",
"name": "Puyallup_station_and_jurisdiction_data",
"crs": { "type": "name", "properties": { "name": "urn:ogc:def:crs:OGC:1.3:CRS84" } },
"features": [
{ "type": "Feature", "properties": { "GISJOIN": "G53056695", "STATEFP": 53, "PLACEFP": 56695, "PLACENS": 2411504, "GEOID": "5356695", "NAME": "Puyallup", "NAMELSAD": "Puyallup city", "LSAD": 25, "CLASSFP": "C1", "PCICBSA": "N", "PCINECTA": "N", "MTFCC": "G4110", "FUNCSTAT": "A", "ALAND": 36610495, "ALAND_sq_mi": 14.13539115, "AWATER": 278481, "INTPTLAT": 47.1792231, "INTPTLON": -122.2891914, "Shape_Leng": 37102.94611, "Shape_Area": 36888984.68, "NHPD_Units": 609, "Permits": 3766, "Pop": 41666, "Pop_density": 2947.636862, "Non_white_share": 0.237075793, "White_non_hisp": 0.762924207, "Black_non_hisp": 0.033912543, "Asian_non_Hisp": 0.059424951, "Hispanic": 0.062184995, "Workers": 20316, "Transit_to_work": 0.050649734, "Walk_to_Work": 0.015308132, "Bike_to_work": 0.0, "Green_commute_share": 0.065957866, "BA_plus_25_plus": 0.267504855, "Med_HH_inc": 76565, "Cost_burdened": 0.47736405, "Very_cost_burdened": 0.177873024, "Med_housing_value": 352800, "Jobs": 30197, "Job_density": 2136.269148, "Housing_units": 16845, "Housing_density": 357.0427594, "Permit_density": 266.4234729, "Permits_per_capita": 90.38544617, "Subsidized_hsg_share": 0.036153161, "existing_housing_units": 1448, "baseline_under_zoning": 7020, "plexify_reform": 8266, "multiply_reform": 10347, "legalize_reform": 10089, "middle_reform": 7020, "all_reforms": 14662, "station_link": "Puyallup-Sounder-Commuter Rail-existing", "existing_housing_units.1": 2993, "baseline_under_zoning.1": 9131, "plexify_reform.1": 10404, "multiply_reform.1": 13969, "legalize_reform.1": 12200, "middle_reform.1": 9131, "all_reforms.1": 18311, "grade": "at grade", "status": "existing", "year_open": 2001, "mode": "Commuter Rail", "line": "Sounder" }, "geometry": { "type": "Point", "coordinates": [ -122.29507, 47.19269 ] } }
]
}
